LICENSE
MANIFEST.in
README.md
README.rst
THANKS
setup.py
bipython/__init__.py
bipython/inspection_standalone.py
bipython.egg-info/PKG-INFO
bipython.egg-info/SOURCES.txt
bipython.egg-info/dependency_links.txt
bipython.egg-info/entry_points.txt
bipython.egg-info/not-zip-safe
bipython.egg-info/requires.txt
bipython.egg-info/top_level.txt