Metadata-Version: 1.1
Name: bipython
Version: 0.1.3.-894b734-
Summary: bipython: the boldly indiscriminate python interpreter
Home-page: http://bipython.org/
Author: Paul Ivanov
Author-email: pi@berkeley.edu
License: UNKNOWN
Download-URL: https://github.com/ivanov/bipython/zipball/0.1
Keywords: Interactive,Interpreter,Shell,bpython,ipython,urwid
Platform: UNKNOWN
Classifier: License :: OSI Approved :: BSD License
Classifier: Development Status :: 3 - Alpha
Classifier: Environment :: Console
Classifier: Intended Audience :: Developers
Classifier: Programming Language :: Python
Classifier: Operating System :: OS Independent
Classifier: Topic :: Software Development :: Interpreters
Classifier: Topic :: Utilities
